LICENSE
MANIFEST.in
README.rst
setup.cfg
setup.py
django_graphql_auth_django_4.egg-info/PKG-INFO
django_graphql_auth_django_4.egg-info/SOURCES.txt
django_graphql_auth_django_4.egg-info/dependency_links.txt
django_graphql_auth_django_4.egg-info/not-zip-safe
django_graphql_auth_django_4.egg-info/requires.txt
django_graphql_auth_django_4.egg-info/top_level.txt
graphql_auth/__init__.py
graphql_auth/apps.py
graphql_auth/backends.py
graphql_auth/bases.py
graphql_auth/constants.py
graphql_auth/decorators.py
graphql_auth/exceptions.py
graphql_auth/forms.py
graphql_auth/mixins.py
graphql_auth/models.py
graphql_auth/mutations.py
graphql_auth/relay.py
graphql_auth/schema.py
graphql_auth/settings.py
graphql_auth/shortcuts.py
graphql_auth/signals.py
graphql_auth/types.py
graphql_auth/utils.py
graphql_auth/migrations/0001_initial.py
graphql_auth/migrations/__init__.py
graphql_auth/templates/email/activation_email.html
graphql_auth/templates/email/activation_subject.txt
graphql_auth/templates/email/password_reset_email.html
graphql_auth/templates/email/password_reset_subject.txt
graphql_auth/templates/email/password_set_email.html
graphql_auth/templates/email/password_set_subject.txt
testproject/__init__.py
testproject/manage.py
testproject/pseudo_async_email_support.py
testproject/schema.py
testproject/settings.py
testproject/urls.py
tests/testCases.py
tests/test_app_settings.py
tests/test_archive_account.py
tests/test_delete_account.py
tests/test_login.py
tests/test_password_change.py
tests/test_password_reset.py
tests/test_password_set.py
tests/test_query.py
tests/test_refresh_token.py
tests/test_register.py
tests/test_remove_secondary_email.py
tests/test_resend_activation_email.py
tests/test_revoke_token.py
tests/test_send_password_reset_email.py
tests/test_send_secondary_email_activation.py
tests/test_swap_emails.py
tests/test_update_account.py
tests/test_verify_account.py
tests/test_verify_secondary_email.py
tests/test_verify_token.py