Metadata-Version: 2.1
Name: django-graphql-auth-django-4
Version: 0.3.16
Summary: Graphql and relay authentication with Graphene for Django.
Home-page: https://github.com/PedroBern/django-graphql-auth
Author: pedrobern
Author-email: pedrobermoreira@gmail.com
Maintainer: pedrobern
License: MIT
Project-URL: Documentation, https://django-graphql-auth.readthedocs.io/en/latest/
Project-URL: Issues, https://github.com/PedroBern/django-graphql-auth/issues
Keywords: api graphql rest relay graphene auth
Classifier: Development Status :: 4 - Beta
Classifier: Environment :: Web Environment
Classifier: Intended Audience :: Developers
Classifier: License :: OSI Approved :: MIT License
Classifier: Operating System :: OS Independent
Classifier: Programming Language :: Python
Classifier: Programming Language :: Python :: 3.6
Classifier: Programming Language :: Python :: 3.7
Classifier: Programming Language :: Python :: 3.8
Classifier: Framework :: Django
Classifier: Framework :: Django :: 2.2
Classifier: Framework :: Django :: 3.0
License-File: LICENSE
Requires-Dist: Django>=2.2.0
Requires-Dist: django-graphql-jwt==0.3.0
Requires-Dist: django-filter>=2.2.0
Requires-Dist: graphene_django>=2.1.8
Requires-Dist: graphene>=2.1.8
Requires-Dist: PyJWT<2.0.0
Provides-Extra: test
Requires-Dist: pytest>=3.6.3; extra == "test"
Requires-Dist: pytest-cov>=2.4.0; extra == "test"
Requires-Dist: pytest-django>=3.1.2; extra == "test"
Requires-Dist: coveralls; extra == "test"
Provides-Extra: dev
Requires-Dist: black==19.3b0; extra == "dev"
Requires-Dist: flake8==3.7.7; extra == "dev"
Requires-Dist: pytest>=3.6.3; extra == "dev"
Requires-Dist: pytest-cov>=2.4.0; extra == "dev"
Requires-Dist: pytest-django>=3.1.2; extra == "dev"
Requires-Dist: coveralls; extra == "dev"
